m2io_nextgen-0.2.1.dist-info/METADATA
m2io_nextgen-0.2.1.dist-info/WHEEL
m2io_nextgen-0.2.1.dist-info/licenses/LICENSE
m2io_nextgen/__init__.py
m2io_nextgen/m2io_nextgen.cp312-win_amd64.pyd
m2io_nextgen-0.2.1.dist-info/RECORD
