Metadata-Version: 2.4
Name: m2io_nextgen
Version: 0.2.1
Classifier: Programming Language :: Rust
Classifier: Programming Language :: Python :: Implementation :: CPython
Classifier: Programming Language :: Python :: Implementation :: PyPy
License-File: LICENSE
License: EUPL-1.2
Requires-Python: >=3.8
